audio/__init__.py
rest_python3_client-0.0.1.dist-info/DESCRIPTION.rst
rest_python3_client-0.0.1.dist-info/METADATA
rest_python3_client-0.0.1.dist-info/RECORD
rest_python3_client-0.0.1.dist-info/WHEEL
rest_python3_client-0.0.1.dist-info/metadata.json
rest_python3_client-0.0.1.dist-info/top_level.txt
