Metadata-Version: 2.0
Name: rest-python3-client
Version: 0.0.1
Summary: My first Python package
Home-page: UNKNOWN
Author: Jason Dsouza
Author-email: chaithrags@gnani.ai
License: UNKNOWN
Keywords: python,first package
Platform: UNKNOWN
Classifier: Development Status :: 3 - Alpha
Classifier: Intended Audience :: Education
Classifier: Programming Language :: Python :: 2
Classifier: Programming Language :: Python :: 3
Classifier: Operating System :: MacOS :: MacOS X
Classifier: Operating System :: Microsoft :: Windows
Requires-Dist: requests
